dsmc/__init__.py
dsmc-0.0.3.dist-info/LICENSE
dsmc-0.0.3.dist-info/METADATA
dsmc-0.0.3.dist-info/WHEEL
dsmc-0.0.3.dist-info/top_level.txt
dsmc-0.0.3.dist-info/RECORD
